archivum/__init__.py
archivum/__version__.py
archivum/cli.py
archivum/document.py
archivum/hasher.py
archivum/library.py
archivum/mendeley_port.py
archivum/parser.py
archivum/querier.py
archivum/reference.py
archivum/trie.py
archivum/utilities.py
archivum-0.2.0.dist-info/licenses/LICENSE
archivum-0.2.0.dist-info/METADATA
archivum-0.2.0.dist-info/WHEEL
archivum-0.2.0.dist-info/entry_points.txt
archivum-0.2.0.dist-info/top_level.txt
archivum-0.2.0.dist-info/RECORD
