Metadata-Version: 2.4
Name: archivum
Version: 0.2.0
Summary: PDF Reference Manager.
Author-email: Stephen J Mildenhall <mynl@me.com>
License: MIT
Project-URL: Source Code, https://github.com/mynl/archivum_project
Classifier: Development Status :: 4 - Beta
Classifier: License :: OSI Approved :: MIT License
Classifier: Programming Language :: Python :: 3.10
Classifier: Topic :: Utilities
Requires-Python: >=3.10
License-File: LICENSE
Requires-Dist: click
Requires-Dist: greater_tables
Requires-Dist: numpy
Requires-Dist: pandas
Requires-Dist: prompt_toolkit
Requires-Dist: pyarrow
Requires-Dist: pyyaml
Requires-Dist: aggregate
Provides-Extra: dev
Requires-Dist: docutils<0.17; extra == "dev"
Requires-Dist: jupyter-sphinx; extra == "dev"
Requires-Dist: nbsphinx; extra == "dev"
Requires-Dist: pickleshare; extra == "dev"
Requires-Dist: recommonmark>=0.7.1; extra == "dev"
Requires-Dist: setuptools>=62.3.2; extra == "dev"
Requires-Dist: sphinx>=5.0; extra == "dev"
Requires-Dist: sphinx-panels; extra == "dev"
Requires-Dist: sphinx-rtd-dark-mode; extra == "dev"
Requires-Dist: sphinxcontrib-bibtex; extra == "dev"
Requires-Dist: sphinx-copybutton; extra == "dev"
Requires-Dist: sphinx-toggleprompt; extra == "dev"
Requires-Dist: sphinx-multitoc-numbering; extra == "dev"
Dynamic: license-file
